m.py
mmm-0.4.2.dist-info/DESCRIPTION.rst
mmm-0.4.2.dist-info/METADATA
mmm-0.4.2.dist-info/RECORD
mmm-0.4.2.dist-info/WHEEL
mmm-0.4.2.dist-info/entry_points.txt
mmm-0.4.2.dist-info/metadata.json
mmm-0.4.2.dist-info/top_level.txt
